rushia_clipper/__init__.py
rushia_clipper/audio.py
rushia_clipper/clipSync.py
rushia_clipper/clipper.py
rushia_clipper/workersKV.py
rushia_clipper-0.0.7.dist-info/METADATA
rushia_clipper-0.0.7.dist-info/WHEEL
rushia_clipper-0.0.7.dist-info/top_level.txt
rushia_clipper-0.0.7.dist-info/RECORD
