Metadata-Version: 2.1
Name: rushia-clipper
Version: 0.0.7
Summary: Download, trim, normalize, upload and publish audio clips to Rushia-btn
Home-page: https://github.com/Rushia-cn/Clipper
Author: George Miao
Author-email: gm@georgemiao.com
License: UNKNOWN
Platform: UNKNOWN
Classifier: Programming Language :: Python :: 3
Classifier: License :: OSI Approved :: MIT License
Classifier: Operating System :: OS Independent
Requires-Python: >=3.8
